{"cameraMode":{"drawMode":0,"name":"Shaded","section":"Shading Mode"},"sceneLighting":true,"audioPlay":false,"sceneViewState":{"m_AlwaysRefresh":false,"showFog":true,"showSkybox":true,"showFlares":true,"showImageEffects":true,"showParticleSystems":true,"showVisualEffectGraphs":true,"m_FxEnabled":true},"in2DMode":false,"pivot":{"x":0.1810593605041504,"y":2.6074397563934328,"z":10.924546241760254},"rotation":{"x":0.10820692777633667,"y":-0.7858873009681702,"z":0.14373640716075898,"w":0.5916230082511902},"size":1.0665181875228882,"orthographic":false}